navitia_client/__init__.py
navitia_client/client/__init__.py
navitia_client/client/exceptions.py
navitia_client/client/navitia_client.py
navitia_client/client/apis/__init__.py
navitia_client/client/apis/api_base_client.py
navitia_client/client/apis/arrival_apis.py
navitia_client/client/apis/contributors_apis.py
navitia_client/client/apis/coverage_apis.py
navitia_client/client/apis/datasets_apis.py
navitia_client/client/apis/departure_apis.py
navitia_client/client/apis/equipment_report_apis.py
navitia_client/client/apis/freefloatings_nearby_apis.py
navitia_client/client/apis/inverted_geocoding_apis.py
navitia_client/client/apis/isochrone_apis.py
navitia_client/client/apis/journeys_apis.py
navitia_client/client/apis/line_report_apis.py
navitia_client/client/apis/place_apis.py
navitia_client/client/apis/places_nearby_apis.py
navitia_client/client/apis/public_transport_objects_apis.py
navitia_client/client/apis/route_schedules_apis.py
navitia_client/client/apis/stop_schedules_apis.py
navitia_client/client/apis/terminus_schedules_apis.py
navitia_client/client/apis/traffic_report_apis.py
navitia_client/client/apis/public_transportation_apis/__init__.py
navitia_client/client/apis/public_transportation_apis/commercial_mode_apis.py
navitia_client/client/apis/public_transportation_apis/company_apis.py
navitia_client/client/apis/public_transportation_apis/disruption_apis.py
navitia_client/client/apis/public_transportation_apis/entity_apis.py
navitia_client/client/apis/public_transportation_apis/line_apis.py
navitia_client/client/apis/public_transportation_apis/network_apis.py
navitia_client/client/apis/public_transportation_apis/physical_mode_apis.py
navitia_client/client/apis/public_transportation_apis/route_apis.py
navitia_client/client/apis/public_transportation_apis/stop_area_apis.py
navitia_client/client/apis/public_transportation_apis/stop_point_apis.py
navitia_client/client/apis/public_transportation_apis/vehicle_journey_apis.py
navitia_client/client/raw/__init__.py
python_navitia_client-2.0.0.dist-info/licenses/LICENSE
python_navitia_client-2.0.0.dist-info/METADATA
python_navitia_client-2.0.0.dist-info/WHEEL
python_navitia_client-2.0.0.dist-info/top_level.txt
python_navitia_client-2.0.0.dist-info/RECORD
