Metadata-Version: 2.4
Name: python-navitia-client
Version: 2.0.0
Summary: Python library to use with Navitia APIs
Author-email: Jonathan Perron <jonathan@perron.bzh>
License: MIT License
Project-URL: Source, https://github.com/jonperron/python-navitia-client
Classifier: Development Status :: 4 - Beta
Classifier: Intended Audience :: Developers
Classifier: Programming Language :: Python :: 3.10
Classifier: Programming Language :: Python :: 3.11
Classifier: Programming Language :: Python :: 3.12
Classifier: Programming Language :: Python :: 3.13
Requires-Python: >=3.10
License-File: LICENSE
Requires-Dist: requests<3,>=2.32
Dynamic: license-file
